mutwo/zimmermann_generators/__init__.py
mutwo/zimmermann_generators/constants.py
mutwo/zimmermann_generators/extended_chomsky.py
mutwo/zimmermann_generators/interlockings.py
mutwo/zimmermann_generators/titles.py
mutwo/zimmermann_version/__init__.py
mutwo.zimmermann-0.5.0.dist-info/LICENSE
mutwo.zimmermann-0.5.0.dist-info/METADATA
mutwo.zimmermann-0.5.0.dist-info/WHEEL
mutwo.zimmermann-0.5.0.dist-info/top_level.txt
mutwo.zimmermann-0.5.0.dist-info/RECORD
