Metadata-Version: 2.1
Name: mutwo.zimmermann
Version: 0.5.0
Summary: zimmermann extension for event based framework for generative art
Home-page: https://github.com/mutwo-org/mutwo.zimmermann
Author: Levin Eric Zimmermann
Author-email: levin.eric.zimmermann@posteo.eu
License: GPL
Project-URL: Documentation, https://mutwo.readthedocs.io/en/latest/
Requires-Python: >=3.9, <4
License-File: LICENSE
Requires-Dist: sympy (<2.0.0,>=1.10.1)
Requires-Dist: mutwo.core (<1.0.0,>=0.62.0)
Requires-Dist: mutwo.music (<1.0.0,>=0.18.0)
Requires-Dist: mutwo.common (<1.0.0,>=0.9.0)
Provides-Extra: testing
Requires-Dist: nose ; extra == 'testing'
Requires-Dist: coveralls ; extra == 'testing'
